[
    {
        "type": "File",
        "name": "c:\\Users\\iluca\\source\\repos\\Logidons-2019\\AngularSite\\src\\app\\don\\newdon\\newdon.component.ts",
        "parent_id": null,
        "fsPath": "c:\\Users\\iluca\\source\\repos\\Logidons-2019\\AngularSite\\src\\app\\don\\newdon\\newdon.component.ts",
        "workspaceRoot": null,
        "workspacePath": null,
        "id": "6gNHZU0xKLhIvjQP"
    },
    {
        "type": "File",
        "name": "c:\\Users\\iluca\\source\\repos\\Logidons-2019\\AngularSite\\src\\app\\don\\newdon\\newdon.component.html",
        "parent_id": null,
        "fsPath": "c:\\Users\\iluca\\source\\repos\\Logidons-2019\\AngularSite\\src\\app\\don\\newdon\\newdon.component.html",
        "workspaceRoot": null,
        "workspacePath": null,
        "id": "niXuYT2oQvRCadMS"
    },
    {
        "type": "File",
        "name": "c:\\Users\\iluca\\source\\repos\\Logidons-2019\\AngularSite\\src\\app\\user\\newuser\\newuser.component.ts",
        "parent_id": null,
        "fsPath": "c:\\Users\\iluca\\source\\repos\\Logidons-2019\\AngularSite\\src\\app\\user\\newuser\\newuser.component.ts",
        "workspaceRoot": null,
        "workspacePath": null,
        "id": "Bfr2x8WoyvL6ksIh"
    },
    {
        "type": "File",
        "name": "c:\\Users\\iluca\\source\\repos\\Logidons-2019\\AngularSite\\src\\app\\user\\newuser\\newuser.component.html",
        "parent_id": null,
        "fsPath": "c:\\Users\\iluca\\source\\repos\\Logidons-2019\\AngularSite\\src\\app\\user\\newuser\\newuser.component.html",
        "workspaceRoot": null,
        "workspacePath": null,
        "id": "uWpOSVMc62qTN50b"
    }
]
